Dodecaregress/__init__.py
Dodecaregress/dodecahedron.py
Dodecaregress/main.py
Dodecaregress/pentagon.py
Dodecaregress/plotting.py
Dodecaregress/transformations.py
dodecaregress/Center_face_rotations.npy
dodecaregress/Center_face_translations.npy
dodecaregress/__init__.py
dodecaregress/dodecahedron.py
dodecaregress/main.py
dodecaregress/pentagon.py
dodecaregress/plotting.py
dodecaregress/transformations.py
dodecaregress-0.0.11.dist-info/METADATA
dodecaregress-0.0.11.dist-info/WHEEL
dodecaregress-0.0.11.dist-info/entry_points.txt
dodecaregress-0.0.11.dist-info/top_level.txt
dodecaregress-0.0.11.dist-info/RECORD
