Metadata-Version: 2.1
Name: dodecaregress
Version: 0.0.11
Summary: Visualize dodecahedron
Home-page: https://github.com/Velythyl/s2i2a
Author: Charlie Gauthier
Author-email: charlie.gauthier@umontreal.ca
License: MIT
Requires-Dist: numpy
Requires-Dist: scipy
Requires-Dist: matplotlib
